pydantic_dbmodel_core/__init__.py
pydantic_dbmodel_core/main.py
pydantic_dbmodel_core/meta.py
pydantic_dbmodel_core/version.py
pydantic_dbmodel_core-0.0.3.dist-info/METADATA
pydantic_dbmodel_core-0.0.3.dist-info/WHEEL
pydantic_dbmodel_core-0.0.3.dist-info/licenses/LICENSE
pydantic_dbmodel_core-0.0.3.dist-info/RECORD
