Metadata-Version: 2.1
Name: pydantic-dbmodel-core
Version: 0.0.3
Summary: Enabling the coexistence of class variables and instance variables with identical names on Pydantic
Project-URL: Homepage, https://github.com/mauro-andre/pydantic-dbmodel-core
Author-email: Mauro André <eng.mauroandre@gmail.com>
License-Expression: MIT
License-File: LICENSE
Classifier: License :: OSI Approved :: MIT License
Classifier: Operating System :: OS Independent
Classifier: Programming Language :: Python :: 3.11
Classifier: Topic :: Database
Classifier: Topic :: Database :: Database Engines/Servers
Requires-Python: >=3.11
Requires-Dist: pydantic<2.7.0,>=2.6.0
